simple_computer/Ui_computer.py
simple_computer/__init__.py
simple_computer/computer.ui
simple_computer/main.py
simple_computer-0.0.1.dist-info/METADATA
simple_computer-0.0.1.dist-info/WHEEL
simple_computer-0.0.1.dist-info/licenses/LICENSE.txt
simple_computer-0.0.1.dist-info/RECORD
